crypto_exchange_handler/__init__.py
crypto_exchange_handler/binance.py
crypto_exchange_handler/exchange_template.py
crypto_exchange_handler/kucoin.py
crypto_exchange_handler-0.0.6.dist-info/LICENSE.md
crypto_exchange_handler-0.0.6.dist-info/WHEEL
crypto_exchange_handler-0.0.6.dist-info/METADATA
crypto_exchange_handler-0.0.6.dist-info/RECORD
