Metadata-Version: 2.1
Name: crypto-exchange-handler
Version: 0.0.6
Summary: This package provides template class and its implementations to handle crypto exchanges in unified way.
License: MIT
Author: CryptoRalph
Author-email: doxter@protonmail.com
Requires-Python: >=3.8,<4.0
Classifier: License :: OSI Approved :: MIT License
Classifier: Programming Language :: Python :: 3
Classifier: Programming Language :: Python :: 3.10
Classifier: Programming Language :: Python :: 3.8
Classifier: Programming Language :: Python :: 3.9
Requires-Dist: python-binance (>=1.0.16,<2.0.0)
Requires-Dist: requests (>=2.28.1,<3.0.0)
